clientapi_billingo/__init__.py
clientapi_billingo/api_client.py
clientapi_billingo/api_response.py
clientapi_billingo/billingo.py
clientapi_billingo/configuration.py
clientapi_billingo/exceptions.py
clientapi_billingo/py.typed
clientapi_billingo/rest.py
clientapi_billingo/api/__init__.py
clientapi_billingo/api/bank_account_api.py
clientapi_billingo/api/currency_api.py
clientapi_billingo/api/document_api.py
clientapi_billingo/api/document_block_api.py
clientapi_billingo/api/document_export_api.py
clientapi_billingo/api/organization_api.py
clientapi_billingo/api/partner_api.py
clientapi_billingo/api/product_api.py
clientapi_billingo/api/spending_api.py
clientapi_billingo/api/util_api.py
clientapi_billingo/models/__init__.py
clientapi_billingo/models/address.py
clientapi_billingo/models/bank_account.py
clientapi_billingo/models/bank_account_list.py
clientapi_billingo/models/category.py
clientapi_billingo/models/check_tax_number_message.py
clientapi_billingo/models/client_error.py
clientapi_billingo/models/client_error_response.py
clientapi_billingo/models/conversation_rate.py
clientapi_billingo/models/correction_type.py
clientapi_billingo/models/country.py
clientapi_billingo/models/create_document_export.py
clientapi_billingo/models/currency.py
clientapi_billingo/models/date_type.py
clientapi_billingo/models/discount.py
clientapi_billingo/models/discount_type.py
clientapi_billingo/models/document.py
clientapi_billingo/models/document_ancestor.py
clientapi_billingo/models/document_bank_account.py
clientapi_billingo/models/document_block.py
clientapi_billingo/models/document_block_list.py
clientapi_billingo/models/document_block_type.py
clientapi_billingo/models/document_cancellation.py
clientapi_billingo/models/document_export_filter_extra.py
clientapi_billingo/models/document_export_id.py
clientapi_billingo/models/document_export_other_options.py
clientapi_billingo/models/document_export_query_type.py
clientapi_billingo/models/document_export_sort_by.py
clientapi_billingo-2.1.0.dist-info/licenses/LICENSE
clientapi_billingo-2.1.0.dist-info/METADATA
clientapi_billingo-2.1.0.dist-info/WHEEL
clientapi_billingo-2.1.0.dist-info/top_level.txt
clientapi_billingo-2.1.0.dist-info/RECORD
