Metadata-Version: 2.4
Name: clientapi-billingo
Version: 2.1.0
Summary: Billingo API v3
Home-page: https://github.com/client-api/billingo-python
Author: Billingo Support
Author-email: hello@billingo.hu
Keywords: OpenAPI,OpenAPI-Generator,Billingo API v3
License-File: LICENSE
Requires-Dist: urllib3<3.0.0,>=1.25.3
Requires-Dist: python-dateutil>=2.8.2
Requires-Dist: pydantic>=2
Requires-Dist: typing-extensions>=4.7.1
Dynamic: author
Dynamic: author-email
Dynamic: description
Dynamic: description-content-type
Dynamic: home-page
Dynamic: keywords
Dynamic: license-file
Dynamic: requires-dist
Dynamic: summary
